aassddee/RF.py
aassddee/__init__.py
aassddee-0.0.3.dist-info/License.txt
aassddee-0.0.3.dist-info/METADATA
aassddee-0.0.3.dist-info/WHEEL
aassddee-0.0.3.dist-info/top_level.txt
aassddee-0.0.3.dist-info/RECORD
